cognite_toolkit/__init__.py
cognite_toolkit/_cdf.py
cognite_toolkit/_cdf_tk/__init__.py
cognite_toolkit/_cdf_tk/apps/__init__.py
cognite_toolkit/_cdf_tk/apps/_auth_app.py
cognite_toolkit/_cdf_tk/apps/_core_app.py
cognite_toolkit/_cdf_tk/apps/_data_app.py
cognite_toolkit/_cdf_tk/apps/_dev_app.py
cognite_toolkit/_cdf_tk/apps/_download_app.py
cognite_toolkit/_cdf_tk/apps/_dump_app.py
cognite_toolkit/_cdf_tk/apps/_import_app.py
cognite_toolkit/_cdf_tk/apps/_landing_app.py
cognite_toolkit/_cdf_tk/apps/_migrate_app.py
cognite_toolkit/_cdf_tk/apps/_modules_app.py
cognite_toolkit/_cdf_tk/apps/_profile_app.py
cognite_toolkit/_cdf_tk/apps/_purge.py
cognite_toolkit/_cdf_tk/apps/_repo_app.py
cognite_toolkit/_cdf_tk/apps/_run.py
cognite_toolkit/_cdf_tk/apps/_upload_app.py
cognite_toolkit/_cdf_tk/builders/__init__.py
cognite_toolkit/_cdf_tk/builders/_base.py
cognite_toolkit/_cdf_tk/builders/_datamodels.py
cognite_toolkit/_cdf_tk/builders/_file.py
cognite_toolkit/_cdf_tk/builders/_function.py
cognite_toolkit/_cdf_tk/builders/_location.py
cognite_toolkit/_cdf_tk/builders/_raw.py
cognite_toolkit/_cdf_tk/builders/_streamlit.py
cognite_toolkit/_cdf_tk/builders/_transformation.py
cognite_toolkit/_cdf_tk/cdf_toml.py
cognite_toolkit/_cdf_tk/client/__init__.py
cognite_toolkit/_cdf_tk/client/_constants.py
cognite_toolkit/_cdf_tk/client/_resource_base.py
cognite_toolkit/_cdf_tk/client/_toolkit_client.py
cognite_toolkit/_cdf_tk/client/api/__init__.py
cognite_toolkit/_cdf_tk/client/api/agents.py
cognite_toolkit/_cdf_tk/client/api/annotations.py
cognite_toolkit/_cdf_tk/client/api/assets.py
cognite_toolkit/_cdf_tk/client/api/containers.py
cognite_toolkit/_cdf_tk/client/api/data_models.py
cognite_toolkit/_cdf_tk/client/api/datasets.py
cognite_toolkit/_cdf_tk/client/api/events.py
cognite_toolkit/_cdf_tk/client/api/extraction_pipelines.py
cognite_toolkit/_cdf_tk/client/api/filemetadata.py
cognite_toolkit/_cdf_tk/client/api/function_schedules.py
cognite_toolkit/_cdf_tk/client/api/functions.py
cognite_toolkit-0.7.69.dist-info/WHEEL
cognite_toolkit-0.7.69.dist-info/entry_points.txt
cognite_toolkit-0.7.69.dist-info/METADATA
cognite_toolkit-0.7.69.dist-info/RECORD
