Metadata-Version: 2.4
Name: cognite_toolkit
Version: 0.7.69
Summary: Official Cognite Data Fusion tool for project templates and configuration deployment
Author: Cognite AS
Author-email: Cognite AS <support@cognite.com>
License-Expression: Apache-2.0
Classifier: Development Status :: 5 - Production/Stable
Classifier: Intended Audience :: Developers
Classifier: Topic :: Software Development :: Build Tools
Classifier: License :: OSI Approved :: Apache Software License
Classifier: Programming Language :: Python :: 3
Classifier: Programming Language :: Python :: 3.10
Classifier: Programming Language :: Python :: 3.11
Classifier: Programming Language :: Python :: 3.12
Classifier: Programming Language :: Python :: 3.13
Classifier: Operating System :: OS Independent
Requires-Dist: python-dotenv>=1.0.0
Requires-Dist: cognite-sdk>=7.87.0,<8.0.0
Requires-Dist: httpx>=0.28.1
Requires-Dist: pandas>=1.5.3,<3.0.0
Requires-Dist: pyyaml>=6.0.1
Requires-Dist: typer>=0.12.0,<1.0.0
Requires-Dist: rich>=13.9.4
Requires-Dist: questionary>=2.0.1
Requires-Dist: tomli>=2.0.1,<3.0.0 ; python_full_version < '3.11'
Requires-Dist: packaging>=25
Requires-Dist: typing-extensions>=4.0.0
Requires-Dist: toml>=0.10.2
Requires-Dist: sentry-sdk>=2.1.0
Requires-Dist: mixpanel>=4.10.1
Requires-Dist: pydantic>=2.11.0
Requires-Dist: python-dateutil>=2.9.0
Requires-Dist: pip>=25.0.1
Requires-Dist: filelock>=3.18.0
Requires-Dist: sqlparse>=0.5.3 ; extra == 'sql'
Requires-Dist: pyarrow>=20.0.0 ; extra == 'table'
Requires-Dist: openpyxl>=3.1.5 ; extra == 'table'
Requires-Python: >=3.10
Project-URL: Homepage, https://docs.cognite.com/cdf/deploy/cdf_toolkit/
Project-URL: Changelog, https://github.com/cognitedata/toolkit/releases
Project-URL: GitHub, https://github.com/cognitedata/toolkit
Project-URL: Documentation, https://docs.cognite.com/cdf/deploy/cdf_toolkit/references/resource_library
Provides-Extra: sql
Provides-Extra: table
